qaservicedetect/__init__.py
quantaxis_servicedetect-0.0.3.dist-info/METADATA
quantaxis_servicedetect-0.0.3.dist-info/WHEEL
quantaxis_servicedetect-0.0.3.dist-info/entry_points.txt
quantaxis_servicedetect-0.0.3.dist-info/top_level.txt
quantaxis_servicedetect-0.0.3.dist-info/zip-safe
quantaxis_servicedetect-0.0.3.dist-info/RECORD
