Metadata-Version: 2.1
Name: quantaxis-servicedetect
Version: 0.0.3
Summary: qaservicedetect
Home-page: https://github.com/yutiansut/qaservicedetect
Author: yutiansut
Author-email: yutiansut@qq.com
License: MIT
Keywords: quantaxis,quant,finance,Backtest,Framework
Platform: UNKNOWN
Classifier: License :: OSI Approved :: MIT License
Classifier: Programming Language :: Python
Classifier: Intended Audience :: Developers
Classifier: Operating System :: OS Independent
Requires-Dist: pika (==1.0.0b1)
Requires-Dist: pymongo
Requires-Dist: click
